oxtapus/__init__.py
oxtapus/fipiran.py
oxtapus/rahavard.py
oxtapus/tgju.py
oxtapus/tsetmc.py
oxtapus/models/__init__.py
oxtapus/models/fipiran.py
oxtapus/models/rahavard.py
oxtapus/models/tsetmc.py
oxtapus/utils/__init__.py
oxtapus/utils/columns.py
oxtapus/utils/models.py
oxtapus/utils/normalize.py
oxtapus/utils/http/__init__.py
oxtapus/utils/http/requests.py
oxtapus-0.4.0.dist-info/licenses/LICENSE.txt
oxtapus-0.4.0.dist-info/METADATA
oxtapus-0.4.0.dist-info/WHEEL
oxtapus-0.4.0.dist-info/top_level.txt
oxtapus-0.4.0.dist-info/RECORD
