Metadata-Version: 2.4
Name: oxtapus
Version: 0.4.0
Summary: گرد-آورِیِ داده هایِ بورسِ تهران و مربوط به آن
Author-email: Yaghoub Ghadri <ghaderi.yaghoub@gmail.com>
Project-URL: Repository, https://github.com/yghaderi/oxtapus
Requires-Python: <3.14,>=3.11
License-File: LICENSE.txt
Requires-Dist: httpx>=0.28.1
Requires-Dist: jdatetime>=5.2.0
Requires-Dist: polars>=1.29.0
Requires-Dist: pydantic>=2.11.4
Requires-Dist: requests>=2.32.3
Requires-Dist: tenacity>=9.1.2
Dynamic: license-file
